README.md
setup.py
asciigit.egg-info/PKG-INFO
asciigit.egg-info/SOURCES.txt
asciigit.egg-info/dependency_links.txt
asciigit.egg-info/entry_points.txt
asciigit.egg-info/requires.txt
asciigit.egg-info/top_level.txt
src/__init__.py
src/colour.py
src/main.py
src/models.py
src/views.py
tests/__init__.py
tests/fixtures.py
tests/test_models.py