Metadata-Version: 2.1
Name: asciigit
Version: 0.0.16
Summary: A command line ASCII Git GUI
Home-page: https://github.com/tommyclark/asciigit
